spectrumtools/__init__.py
spectrumtools/denoise.py
spectrumtools/preprocess.py
spectrumtools/denoise/__init__.py
spectrumtools/denoise/kernel.py
spectrumtools-0.0.3.dist-info/LICENSE
spectrumtools-0.0.3.dist-info/METADATA
spectrumtools-0.0.3.dist-info/WHEEL
spectrumtools-0.0.3.dist-info/top_level.txt
spectrumtools-0.0.3.dist-info/RECORD
