Metadata-Version: 2.1
Name: spectrumtools
Version: 0.0.3
Summary: SpectrumTools is a versatile spectroscopy software platform for comprehensive spectral data analysis and manipulation.
Author-email: Tanuj Chamil <tanujchamil@gmail.com>
Project-URL: Homepage, https://github.com/tanuj-chamil/package_spectrumtools
Project-URL: Bug Tracker, https://github.com/tanuj-chamil/package_spectrumtools/issues
Classifier: Programming Language :: Python :: 3
Classifier: License :: OSI Approved :: GNU General Public License v3 (GPLv3)
Classifier: Operating System :: OS Independent
Requires-Python: >=3.7
License-File: LICENSE
Requires-Dist: numpy
